setup.py
aiy/__init__.py
aiy/audio.py
aiy/cloudspeech.py
aiy/i18n.py
aiy/toneplayer.py
aiy/trackplayer.py
aiy/util.py
aiy/_apis/__init__.py
aiy/_apis/_speech.py
aiy/_drivers/__init__.py
aiy/_drivers/_alsa.py
aiy/_drivers/_button.py
aiy/_drivers/_buzzer.py
aiy/_drivers/_led.py
aiy/_drivers/_player.py
aiy/_drivers/_recorder.py
aiy/_drivers/_tts.py
aiy/assistant/__init__.py
aiy/assistant/auth_helpers.py
aiy/assistant/device_helpers.py
aiy/assistant/grpc.py
aiy/assistant/library.py
aiy/test/__init__.py
aiy_voice_only.egg-info/PKG-INFO
aiy_voice_only.egg-info/SOURCES.txt
aiy_voice_only.egg-info/dependency_links.txt
aiy_voice_only.egg-info/requires.txt
aiy_voice_only.egg-info/top_level.txt
examples/buzzer/buzzer_demo.py
examples/buzzer/buzzer_tracker_demo.py
examples/voice/assistant_grpc_demo.py
examples/voice/assistant_library_demo.py
examples/voice/assistant_library_with_local_commands_demo.py
examples/voice/cloudspeech_demo.py