Metadata-Version: 1.2
Name: aiy-voice-only
Version: 1
Summary: Use AIY Voice Kit's Software without the Shackle of its Hardware
Home-page: https://github.com/nickoala/aiy-voice-only
Author: Nick Lee
Author-email: lee1nick@yahoo.ca
License: LICENSE.txt
Platform: UNKNOWN
Requires-Python: ~=3.5
